alexa/__init__.py
alexa/request.py
alexa/response.py
alexa/session.py
pyalexa_lambda-1.0.4.dist-info/METADATA
pyalexa_lambda-1.0.4.dist-info/RECORD
pyalexa_lambda-1.0.4.dist-info/WHEEL
pyalexa_lambda-1.0.4.dist-info/top_level.txt
